pdexplorer/__init__.py
pdexplorer/_by.py
pdexplorer/_commandarg.py
pdexplorer/_dataset.py
pdexplorer/_get_custom_attributes.py
pdexplorer/_hotkeys.py
pdexplorer/_patsify.py
pdexplorer/_print.py
pdexplorer/_print_horizontal_line.py
pdexplorer/_profile.py
pdexplorer/_quietly.py
pdexplorer/_search.py
pdexplorer/_stata_slice.py
pdexplorer/_webbrowser.py
pdexplorer/browse copy 2.py
pdexplorer/browse copy.py
pdexplorer/browse.py
pdexplorer/cf.py
pdexplorer/clear.py
pdexplorer/collapse.py
pdexplorer/describe.py
pdexplorer/doedit.py
pdexplorer/drop.py
pdexplorer/egen.py
pdexplorer/export.py
pdexplorer/generate.py
pdexplorer/gsort.py
pdexplorer/histogram.py
pdexplorer/keep.py
pdexplorer/labeldata.py
pdexplorer/labelvariable.py
pdexplorer/lis.py
pdexplorer/logit.py
pdexplorer/merge.py
pdexplorer/order.py
pdexplorer/predict.py
pdexplorer/preserve.py
pdexplorer/regress.py
pdexplorer/rename.py
pdexplorer/replace.py
pdexplorer/reshape.py
pdexplorer/restore.py
pdexplorer/returnlist.py
pdexplorer/sample.py
pdexplorer/save.py
pdexplorer/scatter.py
pdexplorer/sort.py
pdexplorer/summarize.py
pdexplorer/sysuse.py
pdexplorer/tabulate.py
pdexplorer/use.py
pdexplorer/webuse.py
pdexplorer/xpose.py
pdexplorer/base/__init__.py
pdexplorer/not_in_stata/__init__.py
pdexplorer/not_in_stata/_altair_mapper.py
pdexplorer/not_in_stata/histogram.py
pdexplorer/not_in_stata/experimental/__init__.py
pdexplorer/not_in_stata/experimental/bard.py
pdexplorer/not_in_stata/experimental/chatgpt.py
pdexplorer/not_in_stata/experimental/flan_t5_base.py
pdexplorer/not_in_stata/experimental/generate_split.py
pdexplorer/not_in_stata/experimental/nnlinear.py
pdexplorer/not_in_stata/experimental/scatter_seaborn.py
pdexplorer/not_in_stata/experimental/streamlit.py
pdexplorer/not_in_stata/finance/__init__.py
pdexplorer/not_in_stata/finance/mtgprice.py
pdexplorer/not_in_stata/finance/mtgyield.py
pdexplorer/not_in_stata/fine_tuning/__init__.py
pdexplorer/not_in_stata/fine_tuning/_audio_classification.py
pdexplorer-0.0.36.dist-info/LICENSE.txt
pdexplorer-0.0.36.dist-info/METADATA
pdexplorer-0.0.36.dist-info/WHEEL
pdexplorer-0.0.36.dist-info/top_level.txt
pdexplorer-0.0.36.dist-info/RECORD
