Metadata-Version: 2.1
Name: pdexplorer
Version: 0.0.36
Summary: A Stata emulator for Python/pandas
Author: pandichef
Project-URL: Bug Reports, https://github.com/pandichef/pdexplorer/issues
Project-URL: Source, https://github.com/pandichef/pdexplorer
Classifier: Development Status :: 3 - Alpha
Classifier: Intended Audience :: Developers
Classifier: Topic :: Software Development :: Build Tools
Classifier: License :: OSI Approved :: BSD License
Classifier: Programming Language :: Python :: 3.8
Classifier: Programming Language :: Python :: 3.9
Classifier: Programming Language :: Python :: 3.10
Classifier: Programming Language :: Python :: 3.11
Requires-Python: >=3.8, <4
License-File: LICENSE.txt
Requires-Dist: markdown2==2.5.0
Requires-Dist: pyarrow==13.0.0
Requires-Dist: rich
Requires-Dist: requests
Requires-Dist: pandas==1.3.5
Requires-Dist: scipy
Requires-Dist: seaborn
Requires-Dist: altair
Requires-Dist: vegafusion[embed]
Requires-Dist: vega-datasets
Requires-Dist: statsmodels==0.14.0
Requires-Dist: scikit-learn
Requires-Dist: graphviz
Requires-Dist: torch
Requires-Dist: huggingface-hub
Requires-Dist: transformers[torch]
Requires-Dist: evaluate
Requires-Dist: sacrebleu
Requires-Dist: openai==1.3.7
Requires-Dist: datasets
Requires-Dist: ydata-profiling
Requires-Dist: sweetviz
Requires-Dist: dtale
Requires-Dist: gql[all]
Requires-Dist: selenium-wire
Requires-Dist: pynput
Requires-Dist: selenium
Requires-Dist: xlwings
Provides-Extra: dev
Requires-Dist: ipython; extra == "dev"
Requires-Dist: pytest; extra == "dev"
